jax_data/__init__.py
jax_data/data.py
jax_data-0.1.1.dist-info/WHEEL
jax_data-0.1.1.dist-info/METADATA
jax_data-0.1.1.dist-info/RECORD
