Metadata-Version: 2.1
Name: jax-data
Version: 0.1.1
Summary: Native data handling for JAX
Home-page: https://github.com/Ashrit-Yarava/jax-data.git
License: MIT
Keywords: jax,jax-data,data,dataset,datahandling
Author: Ashrit Yarava
Author-email: ashrity01@gmail.com
Requires-Python: >=3.7,<4.0
Classifier: License :: OSI Approved :: MIT License
Classifier: Programming Language :: Python :: 3
Classifier: Programming Language :: Python :: 3.7
Classifier: Programming Language :: Python :: 3.8
Requires-Dist: jax (>=0.1.72,<0.2.0)
Requires-Dist: jaxlib (>=0.1.51,<0.2.0)
Requires-Dist: numpy (>=1.19.0,<2.0.0)
Project-URL: Repository, https://github.com/Ashrit-Yarava/jax-data.git
